detect_probe/__init__.py
detect_probe/presto.py
detect_probe/service.py
detect_probe-0.9.26.dist-info/LICENSE
detect_probe-0.9.26.dist-info/METADATA
detect_probe-0.9.26.dist-info/WHEEL
detect_probe-0.9.26.dist-info/top_level.txt
detect_probe-0.9.26.dist-info/RECORD
