Metadata-Version: 2.1
Name: detect-probe
Version: 0.9.26
Summary: A Prelude Probe for Detect
Home-page: https://github.com/preludeorg
Author: Prelude Research
Author-email: support@prelude.org
Classifier: Programming Language :: Python :: 3
Classifier: License :: OSI Approved :: MIT License
Classifier: Operating System :: OS Independent
Requires-Python: >=3.8
License-File: LICENSE
